{
  "(0, 0)" : "blue_stained_glass",
  "(0, 1)" : "blue_stained_glass",
  "(0, 2)" : "blue_stained_glass",
  "(0, 3)" : "blue_stained_glass",
  "(0, 4)" : "blue_stained_glass",
  "(0, 5)" : "blue_stained_glass",
  "(0, 6)" : "blue_stained_glass",
  "(0, 7)" : "blue_stained_glass",
  "(0, 8)" : "blue_stained_glass",
  "(0, 9)" : "blue_stained_glass",
  "(0, 10)" : "blue_stained_glass",
  "(0, 11)" : "blue_stained_glass",
  "(0, 12)" : "blue_stained_glass",
  "(0, 13)" : "blue_stained_glass",
  "(0, 14)" : "blue_stained_glass",
  "(0, 15)" : "blue_stained_glass",
  "(1, 0)" : "blue_stained_glass",
  "(1, 1)" : "blue_stained_glass",
  "(1, 2)" : "blue_stained_glass",
  "(1, 3)" : "blue_stained_glass",
  "(1, 4)" : "blue_stained_glass",
  "(1, 5)" : "blue_stained_glass",
  "(1, 6)" : "blue_stained_glass",
  "(1, 7)" : "blue_stained_glass",
  "(1, 8)" : "blue_stained_glass",
  "(1, 9)" : "blue_stained_glass",
  "(1, 10)" : "blue_stained_glass",
  "(1, 11)" : "blue_stained_glass",
  "(1, 12)" : "blue_stained_glass",
  "(1, 13)" : "blue_stained_glass",
  "(1, 14)" : "blue_stained_glass",
  "(1, 15)" : "blue_stained_glass",
  "(2, 0)" : "blue_stained_glass",
  "(2, 1)" : "blue_stained_glass",
  "(2, 2)" : "blue_stained_glass",
  "(2, 3)" : "blue_stained_glass",
  "(2, 4)" : "blue_stained_glass",
  "(2, 5)" : "blue_stained_glass",
  "(2, 6)" : "blue_stained_glass",
  "(2, 7)" : "blue_stained_glass",
  "(2, 8)" : "blue_stained_glass",
  "(2, 9)" : "blue_stained_glass",
  "(2, 10)" : "blue_stained_glass",
  "(2, 11)" : "blue_stained_glass",
  "(2, 12)" : "blue_stained_glass",
  "(2, 13)" : "blue_stained_glass",
  "(2, 14)" : "blue_stained_glass",
  "(2, 15)" : "blue_stained_glass",
  "(3, 0)" : "blue_stained_glass",
  "(3, 1)" : "blue_stained_glass",
  "(3, 2)" : "blue_stained_glass",
  "(3, 3)" : "blue_stained_glass",
  "(3, 4)" : "blue_stained_glass",
  "(3, 5)" : "blue_stained_glass",
  "(3, 6)" : "blue_stained_glass",
  "(3, 7)" : "blue_stained_glass",
  "(3, 8)" : "blue_stained_glass",
  "(3, 9)" : "blue_stained_glass",
  "(3, 10)" : "blue_stained_glass",
  "(3, 11)" : "blue_stained_glass",
  "(3, 12)" : "blue_stained_glass",
  "(3, 13)" : "blue_stained_glass",
  "(3, 14)" : "blue_stained_glass",
  "(3, 15)" : "blue_stained_glass",
  "(4, 0)" : "blue_stained_glass",
  "(4, 1)" : "blue_stained_glass",
  "(4, 2)" : "blue_stained_glass",
  "(4, 3)" : "blue_stained_glass",
  "(4, 4)" : "blue_stained_glass",
  "(4, 5)" : "blue_stained_glass",
  "(4, 6)" : "blue_stained_glass",
  "(4, 7)" : "blue_stained_glass",
  "(4, 8)" : "blue_stained_glass",
  "(4, 9)" : "blue_stained_glass",
  "(4, 10)" : "blue_stained_glass",
  "(4, 11)" : "blue_stained_glass",
  "(4, 12)" : "blue_stained_glass",
  "(4, 13)" : "blue_stained_glass",
  "(4, 14)" : "blue_stained_glass",
  "(4, 15)" : "blue_stained_glass",
  "(5, 0)" : "blue_stained_glass",
  "(5, 1)" : "blue_stained_glass",
  "(5, 2)" : "blue_stained_glass",
  "(5, 3)" : "blue_stained_glass",
  "(5, 4)" : "blue_stained_glass",
  "(5, 5)" : "blue_stained_glass",
  "(5, 6)" : "blue_stained_glass",
  "(5, 7)" : "blue_stained_glass",
  "(5, 8)" : "blue_stained_glass",
  "(5, 9)" : "blue_stained_glass",
  "(5, 10)" : "blue_stained_glass",
  "(5, 11)" : "blue_stained_glass",
  "(5, 12)" : "blue_stained_glass",
  "(5, 13)" : "blue_stained_glass",
  "(5, 14)" : "blue_stained_glass",
  "(5, 15)" : "blue_stained_glass",
  "(6, 0)" : "blue_stained_glass",
  "(6, 1)" : "blue_stained_glass",
  "(6, 2)" : "blue_stained_glass",
  "(6, 3)" : "blue_stained_glass",
  "(6, 4)" : "blue_stained_glass",
  "(6, 5)" : "blue_stained_glass",
  "(6, 6)" : "blue_stained_glass",
  "(6, 7)" : "blue_stained_glass",
  "(6, 8)" : "blue_stained_glass",
  "(6, 9)" : "blue_stained_glass",
  "(6, 10)" : "blue_stained_glass",
  "(6, 11)" : "blue_stained_glass",
  "(6, 12)" : "blue_stained_glass",
  "(6, 13)" : "blue_stained_glass",
  "(6, 14)" : "blue_stained_glass",
  "(6, 15)" : "blue_stained_glass",
  "(7, 0)" : "blue_stained_glass",
  "(7, 1)" : "blue_stained_glass",
  "(7, 2)" : "blue_stained_glass",
  "(7, 3)" : "blue_stained_glass",
  "(7, 4)" : "blue_stained_glass",
  "(7, 5)" : "blue_stained_glass",
  "(7, 6)" : "blue_stained_glass",
  "(7, 7)" : "blue_stained_glass",
  "(7, 8)" : "blue_stained_glass",
  "(7, 9)" : "blue_stained_glass",
  "(7, 10)" : "blue_stained_glass",
  "(7, 11)" : "blue_stained_glass",
  "(7, 12)" : "blue_stained_glass",
  "(7, 13)" : "blue_stained_glass",
  "(7, 14)" : "blue_stained_glass",
  "(7, 15)" : "blue_stained_glass",
  "(8, 0)" : "blue_stained_glass",
  "(8, 1)" : "blue_stained_glass",
  "(8, 2)" : "blue_stained_glass",
  "(8, 3)" : "blue_stained_glass",
  "(8, 4)" : "blue_stained_glass",
  "(8, 5)" : "blue_stained_glass",
  "(8, 6)" : "blue_stained_glass",
  "(8, 7)" : "blue_stained_glass",
  "(8, 8)" : "blue_stained_glass",
  "(8, 9)" : "blue_stained_glass",
  "(8, 10)" : "blue_stained_glass",
  "(8, 11)" : "blue_stained_glass",
  "(8, 12)" : "blue_stained_glass",
  "(8, 13)" : "blue_stained_glass",
  "(8, 14)" : "blue_stained_glass",
  "(8, 15)" : "blue_stained_glass",
  "(9, 0)" : "blue_stained_glass",
  "(9, 1)" : "blue_stained_glass",
  "(9, 2)" : "blue_stained_glass",
  "(9, 3)" : "blue_stained_glass",
  "(9, 4)" : "blue_stained_glass",
  "(9, 5)" : "blue_stained_glass",
  "(9, 6)" : "blue_stained_glass",
  "(9, 7)" : "blue_stained_glass",
  "(9, 8)" : "blue_stained_glass",
  "(9, 9)" : "blue_stained_glass",
  "(9, 10)" : "blue_stained_glass",
  "(9, 11)" : "blue_stained_glass",
  "(9, 12)" : "blue_stained_glass",
  "(9, 13)" : "blue_stained_glass",
  "(9, 14)" : "blue_stained_glass",
  "(9, 15)" : "blue_stained_glass",
  "(10, 0)" : "blue_stained_glass",
  "(10, 1)" : "blue_stained_glass",
  "(10, 2)" : "blue_stained_glass",
  "(10, 3)" : "blue_stained_glass",
  "(10, 4)" : "blue_stained_glass",
  "(10, 5)" : "blue_stained_glass",
  "(10, 6)" : "blue_stained_glass",
  "(10, 7)" : "blue_stained_glass",
  "(10, 8)" : "blue_stained_glass",
  "(10, 9)" : "blue_stained_glass",
  "(10, 10)" : "blue_stained_glass",
  "(10, 11)" : "blue_stained_glass",
  "(10, 12)" : "blue_stained_glass",
  "(10, 13)" : "blue_stained_glass",
  "(10, 14)" : "blue_stained_glass",
  "(10, 15)" : "blue_stained_glass",
  "(11, 0)" : "blue_stained_glass",
  "(11, 1)" : "blue_stained_glass",
  "(11, 2)" : "blue_stained_glass",
  "(11, 3)" : "blue_stained_glass",
  "(11, 4)" : "blue_stained_glass",
  "(11, 5)" : "blue_stained_glass",
  "(11, 6)" : "blue_stained_glass",
  "(11, 7)" : "blue_stained_glass",
  "(11, 8)" : "blue_stained_glass",
  "(11, 9)" : "blue_stained_glass",
  "(11, 10)" : "blue_stained_glass",
  "(11, 11)" : "blue_stained_glass",
  "(11, 12)" : "blue_stained_glass",
  "(11, 13)" : "blue_stained_glass",
  "(11, 14)" : "blue_stained_glass",
  "(11, 15)" : "blue_stained_glass",
  "(12, 0)" : "blue_stained_glass",
  "(12, 1)" : "blue_stained_glass",
  "(12, 2)" : "blue_stained_glass",
  "(12, 3)" : "blue_stained_glass",
  "(12, 4)" : "blue_stained_glass",
  "(12, 5)" : "blue_stained_glass",
  "(12, 6)" : "blue_stained_glass",
  "(12, 7)" : "blue_stained_glass",
  "(12, 8)" : "blue_stained_glass",
  "(12, 9)" : "blue_stained_glass",
  "(12, 10)" : "blue_stained_glass",
  "(12, 11)" : "blue_stained_glass",
  "(12, 12)" : "blue_stained_glass",
  "(12, 13)" : "blue_stained_glass",
  "(12, 14)" : "blue_stained_glass",
  "(12, 15)" : "blue_stained_glass",
  "(13, 0)" : "blue_stained_glass",
  "(13, 1)" : "blue_stained_glass",
  "(13, 2)" : "blue_stained_glass",
  "(13, 3)" : "blue_stained_glass",
  "(13, 4)" : "blue_stained_glass",
  "(13, 5)" : "blue_stained_glass",
  "(13, 6)" : "blue_stained_glass",
  "(13, 7)" : "blue_stained_glass",
  "(13, 8)" : "blue_stained_glass",
  "(13, 9)" : "blue_stained_glass",
  "(13, 10)" : "blue_stained_glass",
  "(13, 11)" : "blue_stained_glass",
  "(13, 12)" : "blue_stained_glass",
  "(13, 13)" : "blue_stained_glass",
  "(13, 14)" : "blue_stained_glass",
  "(13, 15)" : "blue_stained_glass",
  "(14, 0)" : "blue_stained_glass",
  "(14, 1)" : "blue_stained_glass",
  "(14, 2)" : "blue_stained_glass",
  "(14, 3)" : "blue_stained_glass",
  "(14, 4)" : "blue_stained_glass",
  "(14, 5)" : "blue_stained_glass",
  "(14, 6)" : "blue_stained_glass",
  "(14, 7)" : "blue_stained_glass",
  "(14, 8)" : "blue_stained_glass",
  "(14, 9)" : "blue_stained_glass",
  "(14, 10)" : "blue_stained_glass",
  "(14, 11)" : "blue_stained_glass",
  "(14, 12)" : "blue_stained_glass",
  "(14, 13)" : "blue_stained_glass",
  "(14, 14)" : "blue_stained_glass",
  "(14, 15)" : "blue_stained_glass",
  "(15, 0)" : "blue_stained_glass",
  "(15, 1)" : "blue_stained_glass",
  "(15, 2)" : "blue_stained_glass",
  "(15, 3)" : "blue_stained_glass",
  "(15, 4)" : "blue_stained_glass",
  "(15, 5)" : "blue_stained_glass",
  "(15, 6)" : "blue_stained_glass",
  "(15, 7)" : "blue_stained_glass",
  "(15, 8)" : "blue_stained_glass",
  "(15, 9)" : "blue_stained_glass",
  "(15, 10)" : "blue_stained_glass",
  "(15, 11)" : "blue_stained_glass",
  "(15, 12)" : "blue_stained_glass",
  "(15, 13)" : "blue_stained_glass",
  "(15, 14)" : "blue_stained_glass",
  "(15, 15)" : "blue_stained_glass"
}