{
  "(0, 0)" : "stripped_warped_stem",
  "(0, 1)" : "emerald_ore",
  "(0, 2)" : "lapis_ore",
  "(0, 3)" : "cyan_glazed_terracotta",
  "(0, 4)" : "emerald_ore",
  "(0, 5)" : "prismarine",
  "(0, 6)" : "stripped_warped_stem",
  "(0, 7)" : "cyan_stained_glass",
  "(0, 8)" : "cyan_stained_glass",
  "(0, 9)" : "lapis_ore",
  "(0, 10)" : "emerald_ore",
  "(0, 11)" : "cyan_stained_glass",
  "(0, 12)" : "stripped_warped_stem",
  "(0, 13)" : "cyan_glazed_terracotta",
  "(0, 14)" : "cyan_glazed_terracotta",
  "(0, 15)" : "cyan_stained_glass",
  "(0, 16)" : "cyan_stained_glass",
  "(0, 17)" : "emerald_ore",
  "(0, 18)" : "lapis_ore",
  "(0, 19)" : "stripped_warped_stem",
  "(0, 20)" : "emerald_ore",
  "(0, 21)" : "prismarine",
  "(0, 22)" : "stripped_warped_stem",
  "(0, 23)" : "cyan_stained_glass",
  "(0, 24)" : "cyan_stained_glass",
  "(0, 25)" : "cyan_stained_glass",
  "(0, 26)" : "emerald_ore",
  "(0, 27)" : "cyan_stained_glass",
  "(0, 28)" : "stripped_warped_stem",
  "(0, 29)" : "cyan_glazed_terracotta",
  "(0, 30)" : "cyan_glazed_terracotta",
  "(0, 31)" : "cyan_stained_glass",
  "(0, 32)" : "cyan_stained_glass",
  "(0, 33)" : "emerald_ore",
  "(0, 34)" : "cyan_glazed_terracotta",
  "(0, 35)" : "stripped_warped_stem",
  "(0, 36)" : "lapis_ore",
  "(0, 37)" : "emerald_ore",
  "(0, 38)" : "stripped_warped_stem",
  "(0, 39)" : "cyan_stained_glass",
  "(0, 40)" : "emerald_ore",
  "(0, 41)" : "lapis_ore",
  "(0, 42)" : "emerald_ore",
  "(0, 43)" : "cyan_stained_glass",
  "(0, 44)" : "stripped_warped_stem",
  "(0, 45)" : "cyan_glazed_terracotta",
  "(0, 46)" : "stripped_warped_stem",
  "(0, 47)" : "cyan_stained_glass",
  "(0, 48)" : "stripped_warped_stem",
  "(0, 49)" : "lapis_ore",
  "(0, 50)" : "cyan_glazed_terracotta",
  "(0, 51)" : "stripped_warped_stem",
  "(0, 52)" : "cyan_stained_glass",
  "(0, 53)" : "emerald_ore",
  "(0, 54)" : "stripped_warped_stem",
  "(0, 55)" : "cyan_stained_glass",
  "(0, 56)" : "cyan_stained_glass",
  "(0, 57)" : "lapis_ore",
  "(0, 58)" : "emerald_ore",
  "(0, 59)" : "lapis_ore",
  "(0, 60)" : "stripped_warped_stem",
  "(0, 61)" : "cyan_glazed_terracotta",
  "(0, 62)" : "cyan_glazed_terracotta",
  "(0, 63)" : "lapis_ore",
  "(0, 64)" : "cyan_stained_glass",
  "(0, 65)" : "lapis_ore",
  "(0, 66)" : "cyan_glazed_terracotta",
  "(0, 67)" : "stripped_warped_stem",
  "(0, 68)" : "emerald_ore",
  "(0, 69)" : "prismarine",
  "(0, 70)" : "stripped_warped_stem",
  "(0, 71)" : "cyan_stained_glass",
  "(0, 72)" : "cyan_stained_glass",
  "(0, 73)" : "lapis_ore",
  "(0, 74)" : "emerald_ore",
  "(0, 75)" : "cyan_stained_glass",
  "(0, 76)" : "stripped_warped_stem",
  "(0, 77)" : "lapis_ore",
  "(0, 78)" : "cyan_glazed_terracotta",
  "(0, 79)" : "cyan_stained_glass",
  "(1, 0)" : "stripped_warped_stem",
  "(1, 1)" : "stripped_warped_stem",
  "(1, 2)" : "prismarine_bricks",
  "(1, 3)" : "light_gray_glazed_terracotta",
  "(1, 4)" : "sea_lantern",
  "(1, 5)" : "sea_lantern",
  "(1, 6)" : "sea_lantern",
  "(1, 7)" : "white_concrete",
  "(1, 8)" : "white_concrete",
  "(1, 9)" : "white_glazed_terracotta",
  "(1, 10)" : "sea_lantern",
  "(1, 11)" : "sea_lantern",
  "(1, 12)" : "light_gray_glazed_terracotta",
  "(1, 13)" : "prismarine_bricks",
  "(1, 14)" : "lapis_ore",
  "(1, 15)" : "cyan_glazed_terracotta",
  "(1, 16)" : "stripped_warped_stem",
  "(1, 17)" : "stripped_warped_stem",
  "(1, 18)" : "prismarine_bricks",
  "(1, 19)" : "light_gray_glazed_terracotta",
  "(1, 20)" : "sea_lantern",
  "(1, 21)" : "sea_lantern",
  "(1, 22)" : "sea_lantern",
  "(1, 23)" : "white_concrete",
  "(1, 24)" : "white_concrete",
  "(1, 25)" : "white_glazed_terracotta",
  "(1, 26)" : "sea_lantern",
  "(1, 27)" : "sea_lantern",
  "(1, 28)" : "light_gray_glazed_terracotta",
  "(1, 29)" : "prismarine_bricks",
  "(1, 30)" : "stripped_warped_stem",
  "(1, 31)" : "cyan_glazed_terracotta",
  "(1, 32)" : "stripped_warped_stem",
  "(1, 33)" : "stripped_warped_stem",
  "(1, 34)" : "prismarine_bricks",
  "(1, 35)" : "light_gray_glazed_terracotta",
  "(1, 36)" : "sea_lantern",
  "(1, 37)" : "sea_lantern",
  "(1, 38)" : "sea_lantern",
  "(1, 39)" : "white_concrete",
  "(1, 40)" : "white_concrete",
  "(1, 41)" : "white_glazed_terracotta",
  "(1, 42)" : "sea_lantern",
  "(1, 43)" : "sea_lantern",
  "(1, 44)" : "light_gray_glazed_terracotta",
  "(1, 45)" : "prismarine_bricks",
  "(1, 46)" : "stripped_warped_stem",
  "(1, 47)" : "cyan_glazed_terracotta",
  "(1, 48)" : "stripped_warped_stem",
  "(1, 49)" : "stripped_warped_stem",
  "(1, 50)" : "prismarine_bricks",
  "(1, 51)" : "sea_lantern",
  "(1, 52)" : "sea_lantern",
  "(1, 53)" : "white_glazed_terracotta",
  "(1, 54)" : "white_glazed_terracotta",
  "(1, 55)" : "white_concrete",
  "(1, 56)" : "white_concrete",
  "(1, 57)" : "white_glazed_terracotta",
  "(1, 58)" : "sea_lantern",
  "(1, 59)" : "sea_lantern",
  "(1, 60)" : "light_gray_glazed_terracotta",
  "(1, 61)" : "prismarine_bricks",
  "(1, 62)" : "lapis_ore",
  "(1, 63)" : "cyan_glazed_terracotta",
  "(1, 64)" : "stripped_warped_stem",
  "(1, 65)" : "stripped_warped_stem",
  "(1, 66)" : "prismarine_bricks",
  "(1, 67)" : "light_gray_glazed_terracotta",
  "(1, 68)" : "sea_lantern",
  "(1, 69)" : "sea_lantern",
  "(1, 70)" : "sea_lantern",
  "(1, 71)" : "white_concrete",
  "(1, 72)" : "white_concrete",
  "(1, 73)" : "white_glazed_terracotta",
  "(1, 74)" : "sea_lantern",
  "(1, 75)" : "sea_lantern",
  "(1, 76)" : "light_gray_glazed_terracotta",
  "(1, 77)" : "prismarine_bricks",
  "(1, 78)" : "cyan_stained_glass",
  "(1, 79)" : "cyan_glazed_terracotta",
  "(2, 0)" : "stripped_warped_stem",
  "(2, 1)" : "prismarine_bricks",
  "(2, 2)" : "light_gray_glazed_terracotta",
  "(2, 3)" : "white_concrete",
  "(2, 4)" : "iron_block",
  "(2, 5)" : "iron_block",
  "(2, 6)" : "white_concrete_powder",
  "(2, 7)" : "iron_block",
  "(2, 8)" : "white_concrete_powder",
  "(2, 9)" : "iron_block",
  "(2, 10)" : "white_concrete",
  "(2, 11)" : "white_concrete",
  "(2, 12)" : "white_glazed_terracotta",
  "(2, 13)" : "light_gray_glazed_terracotta",
  "(2, 14)" : "prismarine_bricks",
  "(2, 15)" : "cyan_glazed_terracotta",
  "(2, 16)" : "stripped_warped_stem",
  "(2, 17)" : "prismarine_bricks",
  "(2, 18)" : "light_gray_glazed_terracotta",
  "(2, 19)" : "white_concrete",
  "(2, 20)" : "iron_block",
  "(2, 21)" : "iron_block",
  "(2, 22)" : "iron_block",
  "(2, 23)" : "iron_block",
  "(2, 24)" : "white_concrete_powder",
  "(2, 25)" : "white_concrete_powder",
  "(2, 26)" : "white_concrete",
  "(2, 27)" : "white_concrete",
  "(2, 28)" : "white_glazed_terracotta",
  "(2, 29)" : "light_gray_glazed_terracotta",
  "(2, 30)" : "prismarine_bricks",
  "(2, 31)" : "cyan_glazed_terracotta",
  "(2, 32)" : "stripped_warped_stem",
  "(2, 33)" : "prismarine_bricks",
  "(2, 34)" : "light_gray_glazed_terracotta",
  "(2, 35)" : "white_concrete",
  "(2, 36)" : "iron_block",
  "(2, 37)" : "birch_wood",
  "(2, 38)" : "iron_block",
  "(2, 39)" : "iron_block",
  "(2, 40)" : "iron_block",
  "(2, 41)" : "iron_block",
  "(2, 42)" : "iron_block",
  "(2, 43)" : "white_concrete",
  "(2, 44)" : "white_glazed_terracotta",
  "(2, 45)" : "light_gray_glazed_terracotta",
  "(2, 46)" : "prismarine_bricks",
  "(2, 47)" : "cyan_glazed_terracotta",
  "(2, 48)" : "stripped_warped_stem",
  "(2, 49)" : "prismarine_bricks",
  "(2, 50)" : "light_gray_glazed_terracotta",
  "(2, 51)" : "white_concrete",
  "(2, 52)" : "white_concrete",
  "(2, 53)" : "iron_block",
  "(2, 54)" : "iron_block",
  "(2, 55)" : "iron_block",
  "(2, 56)" : "iron_block",
  "(2, 57)" : "iron_block",
  "(2, 58)" : "white_concrete",
  "(2, 59)" : "white_concrete",
  "(2, 60)" : "white_glazed_terracotta",
  "(2, 61)" : "light_gray_glazed_terracotta",
  "(2, 62)" : "prismarine_bricks",
  "(2, 63)" : "cyan_glazed_terracotta",
  "(2, 64)" : "stripped_warped_stem",
  "(2, 65)" : "prismarine_bricks",
  "(2, 66)" : "light_gray_glazed_terracotta",
  "(2, 67)" : "white_concrete",
  "(2, 68)" : "iron_block",
  "(2, 69)" : "iron_block",
  "(2, 70)" : "white_concrete_powder",
  "(2, 71)" : "iron_block",
  "(2, 72)" : "iron_block",
  "(2, 73)" : "iron_block",
  "(2, 74)" : "white_concrete",
  "(2, 75)" : "white_concrete",
  "(2, 76)" : "white_glazed_terracotta",
  "(2, 77)" : "light_gray_glazed_terracotta",
  "(2, 78)" : "prismarine_bricks",
  "(2, 79)" : "cyan_glazed_terracotta",
  "(3, 0)" : "emerald_ore",
  "(3, 1)" : "light_gray_glazed_terracotta",
  "(3, 2)" : "white_concrete",
  "(3, 3)" : "white_concrete",
  "(3, 4)" : "iron_block",
  "(3, 5)" : "white_concrete_powder",
  "(3, 6)" : "white_concrete_powder",
  "(3, 7)" : "white_concrete_powder",
  "(3, 8)" : "white_concrete_powder",
  "(3, 9)" : "white_concrete_powder",
  "(3, 10)" : "white_concrete_powder",
  "(3, 11)" : "white_concrete_powder",
  "(3, 12)" : "white_concrete",
  "(3, 13)" : "white_concrete",
  "(3, 14)" : "light_gray_glazed_terracotta",
  "(3, 15)" : "cyan_glazed_terracotta",
  "(3, 16)" : "emerald_ore",
  "(3, 17)" : "light_gray_glazed_terracotta",
  "(3, 18)" : "white_concrete",
  "(3, 19)" : "white_concrete",
  "(3, 20)" : "iron_block",
  "(3, 21)" : "iron_block",
  "(3, 22)" : "white_concrete_powder",
  "(3, 23)" : "iron_block",
  "(3, 24)" : "white_concrete_powder",
  "(3, 25)" : "white_concrete_powder",
  "(3, 26)" : "iron_block",
  "(3, 27)" : "iron_block",
  "(3, 28)" : "white_concrete",
  "(3, 29)" : "white_concrete",
  "(3, 30)" : "light_gray_glazed_terracotta",
  "(3, 31)" : "cyan_glazed_terracotta",
  "(3, 32)" : "emerald_ore",
  "(3, 33)" : "light_gray_glazed_terracotta",
  "(3, 34)" : "white_concrete",
  "(3, 35)" : "iron_block",
  "(3, 36)" : "iron_block",
  "(3, 37)" : "white_concrete_powder",
  "(3, 38)" : "white_concrete_powder",
  "(3, 39)" : "white_concrete_powder",
  "(3, 40)" : "white_concrete_powder",
  "(3, 41)" : "white_concrete_powder",
  "(3, 42)" : "white_concrete_powder",
  "(3, 43)" : "iron_block",
  "(3, 44)" : "white_concrete",
  "(3, 45)" : "white_concrete",
  "(3, 46)" : "light_gray_glazed_terracotta",
  "(3, 47)" : "cyan_glazed_terracotta",
  "(3, 48)" : "emerald_ore",
  "(3, 49)" : "light_gray_glazed_terracotta",
  "(3, 50)" : "white_concrete",
  "(3, 51)" : "white_concrete",
  "(3, 52)" : "white_concrete_powder",
  "(3, 53)" : "white_concrete_powder",
  "(3, 54)" : "white_concrete_powder",
  "(3, 55)" : "white_concrete_powder",
  "(3, 56)" : "white_concrete_powder",
  "(3, 57)" : "white_concrete_powder",
  "(3, 58)" : "white_concrete_powder",
  "(3, 59)" : "iron_block",
  "(3, 60)" : "white_concrete",
  "(3, 61)" : "white_glazed_terracotta",
  "(3, 62)" : "light_gray_glazed_terracotta",
  "(3, 63)" : "cyan_glazed_terracotta",
  "(3, 64)" : "emerald_ore",
  "(3, 65)" : "light_gray_glazed_terracotta",
  "(3, 66)" : "white_concrete",
  "(3, 67)" : "iron_block",
  "(3, 68)" : "iron_block",
  "(3, 69)" : "white_concrete_powder",
  "(3, 70)" : "white_concrete_powder",
  "(3, 71)" : "white_concrete_powder",
  "(3, 72)" : "white_concrete_powder",
  "(3, 73)" : "white_concrete_powder",
  "(3, 74)" : "white_concrete_powder",
  "(3, 75)" : "iron_block",
  "(3, 76)" : "white_concrete",
  "(3, 77)" : "white_concrete",
  "(3, 78)" : "light_gray_glazed_terracotta",
  "(3, 79)" : "cyan_glazed_terracotta",
  "(4, 0)" : "stripped_warped_stem",
  "(4, 1)" : "light_gray_glazed_terracotta",
  "(4, 2)" : "iron_block",
  "(4, 3)" : "iron_block",
  "(4, 4)" : "white_concrete_powder",
  "(4, 5)" : "white_concrete_powder",
  "(4, 6)" : "white_concrete_powder",
  "(4, 7)" : "white_concrete_powder",
  "(4, 8)" : "white_concrete_powder",
  "(4, 9)" : "white_concrete_powder",
  "(4, 10)" : "white_concrete_powder",
  "(4, 11)" : "white_concrete_powder",
  "(4, 12)" : "white_concrete_powder",
  "(4, 13)" : "white_concrete",
  "(4, 14)" : "light_gray_glazed_terracotta",
  "(4, 15)" : "stripped_warped_stem",
  "(4, 16)" : "cyan_glazed_terracotta",
  "(4, 17)" : "light_gray_glazed_terracotta",
  "(4, 18)" : "iron_block",
  "(4, 19)" : "iron_block",
  "(4, 20)" : "iron_block",
  "(4, 21)" : "white_concrete_powder",
  "(4, 22)" : "white_concrete_powder",
  "(4, 23)" : "white_concrete_powder",
  "(4, 24)" : "white_concrete_powder",
  "(4, 25)" : "white_concrete_powder",
  "(4, 26)" : "white_concrete_powder",
  "(4, 27)" : "iron_block",
  "(4, 28)" : "iron_block",
  "(4, 29)" : "white_concrete",
  "(4, 30)" : "light_gray_glazed_terracotta",
  "(4, 31)" : "stripped_warped_stem",
  "(4, 32)" : "stripped_warped_stem",
  "(4, 33)" : "light_gray_glazed_terracotta",
  "(4, 34)" : "iron_block",
  "(4, 35)" : "iron_block",
  "(4, 36)" : "white_concrete_powder",
  "(4, 37)" : "white_concrete_powder",
  "(4, 38)" : "white_concrete_powder",
  "(4, 39)" : "white_concrete_powder",
  "(4, 40)" : "white_concrete_powder",
  "(4, 41)" : "white_concrete_powder",
  "(4, 42)" : "white_concrete_powder",
  "(4, 43)" : "white_concrete_powder",
  "(4, 44)" : "iron_block",
  "(4, 45)" : "white_concrete",
  "(4, 46)" : "light_gray_glazed_terracotta",
  "(4, 47)" : "stripped_warped_stem",
  "(4, 48)" : "cyan_glazed_terracotta",
  "(4, 49)" : "light_gray_glazed_terracotta",
  "(4, 50)" : "iron_block",
  "(4, 51)" : "iron_block",
  "(4, 52)" : "white_concrete_powder",
  "(4, 53)" : "white_concrete_powder",
  "(4, 54)" : "white_concrete_powder",
  "(4, 55)" : "white_concrete_powder",
  "(4, 56)" : "white_concrete_powder",
  "(4, 57)" : "white_concrete_powder",
  "(4, 58)" : "white_concrete_powder",
  "(4, 59)" : "white_concrete_powder",
  "(4, 60)" : "iron_block",
  "(4, 61)" : "white_concrete",
  "(4, 62)" : "light_gray_glazed_terracotta",
  "(4, 63)" : "cyan_glazed_terracotta",
  "(4, 64)" : "stripped_warped_stem",
  "(4, 65)" : "light_gray_glazed_terracotta",
  "(4, 66)" : "iron_block",
  "(4, 67)" : "iron_block",
  "(4, 68)" : "white_concrete_powder",
  "(4, 69)" : "white_concrete_powder",
  "(4, 70)" : "white_concrete_powder",
  "(4, 71)" : "chiseled_quartz_block",
  "(4, 72)" : "chiseled_quartz_block",
  "(4, 73)" : "white_concrete_powder",
  "(4, 74)" : "white_concrete_powder",
  "(4, 75)" : "white_concrete_powder",
  "(4, 76)" : "iron_block",
  "(4, 77)" : "white_concrete",
  "(4, 78)" : "light_gray_glazed_terracotta",
  "(4, 79)" : "cyan_glazed_terracotta",
  "(5, 0)" : "stripped_warped_stem",
  "(5, 1)" : "white_glazed_terracotta",
  "(5, 2)" : "iron_block",
  "(5, 3)" : "white_concrete_powder",
  "(5, 4)" : "white_concrete_powder",
  "(5, 5)" : "white_concrete_powder",
  "(5, 6)" : "white_wool",
  "(5, 7)" : "white_wool",
  "(5, 8)" : "white_concrete_powder",
  "(5, 9)" : "white_wool",
  "(5, 10)" : "white_concrete_powder",
  "(5, 11)" : "white_concrete_powder",
  "(5, 12)" : "white_concrete_powder",
  "(5, 13)" : "iron_block",
  "(5, 14)" : "light_gray_glazed_terracotta",
  "(5, 15)" : "cyan_glazed_terracotta",
  "(5, 16)" : "stripped_warped_stem",
  "(5, 17)" : "white_glazed_terracotta",
  "(5, 18)" : "iron_block",
  "(5, 19)" : "iron_block",
  "(5, 20)" : "white_concrete_powder",
  "(5, 21)" : "white_concrete_powder",
  "(5, 22)" : "white_concrete_powder",
  "(5, 23)" : "white_wool",
  "(5, 24)" : "white_wool",
  "(5, 25)" : "white_concrete_powder",
  "(5, 26)" : "white_concrete_powder",
  "(5, 27)" : "white_concrete_powder",
  "(5, 28)" : "iron_block",
  "(5, 29)" : "iron_block",
  "(5, 30)" : "light_gray_glazed_terracotta",
  "(5, 31)" : "cyan_glazed_terracotta",
  "(5, 32)" : "cyan_stained_glass",
  "(5, 33)" : "white_glazed_terracotta",
  "(5, 34)" : "iron_block",
  "(5, 35)" : "white_concrete_powder",
  "(5, 36)" : "white_concrete_powder",
  "(5, 37)" : "white_concrete_powder",
  "(5, 38)" : "white_wool",
  "(5, 39)" : "white_concrete_powder",
  "(5, 40)" : "white_concrete_powder",
  "(5, 41)" : "white_concrete_powder",
  "(5, 42)" : "white_concrete_powder",
  "(5, 43)" : "white_concrete_powder",
  "(5, 44)" : "white_concrete_powder",
  "(5, 45)" : "iron_block",
  "(5, 46)" : "light_gray_glazed_terracotta",
  "(5, 47)" : "cyan_glazed_terracotta",
  "(5, 48)" : "stripped_warped_stem",
  "(5, 49)" : "white_glazed_terracotta",
  "(5, 50)" : "iron_block",
  "(5, 51)" : "white_concrete_powder",
  "(5, 52)" : "white_concrete_powder",
  "(5, 53)" : "white_concrete_powder",
  "(5, 54)" : "white_concrete_powder",
  "(5, 55)" : "chiseled_quartz_block",
  "(5, 56)" : "chiseled_quartz_block",
  "(5, 57)" : "white_concrete_powder",
  "(5, 58)" : "white_concrete_powder",
  "(5, 59)" : "white_concrete_powder",
  "(5, 60)" : "white_concrete_powder",
  "(5, 61)" : "iron_block",
  "(5, 62)" : "light_gray_glazed_terracotta",
  "(5, 63)" : "cyan_glazed_terracotta",
  "(5, 64)" : "stripped_warped_stem",
  "(5, 65)" : "white_glazed_terracotta",
  "(5, 66)" : "iron_block",
  "(5, 67)" : "white_concrete_powder",
  "(5, 68)" : "white_concrete_powder",
  "(5, 69)" : "white_concrete_powder",
  "(5, 70)" : "white_concrete_powder",
  "(5, 71)" : "white_concrete_powder",
  "(5, 72)" : "white_concrete_powder",
  "(5, 73)" : "iron_block",
  "(5, 74)" : "white_concrete_powder",
  "(5, 75)" : "white_concrete_powder",
  "(5, 76)" : "white_concrete_powder",
  "(5, 77)" : "iron_block",
  "(5, 78)" : "light_gray_glazed_terracotta",
  "(5, 79)" : "cyan_glazed_terracotta",
  "(6, 0)" : "stripped_warped_stem",
  "(6, 1)" : "sea_lantern",
  "(6, 2)" : "white_concrete_powder",
  "(6, 3)" : "white_concrete_powder",
  "(6, 4)" : "white_concrete_powder",
  "(6, 5)" : "white_wool",
  "(6, 6)" : "white_wool",
  "(6, 7)" : "white_concrete_powder",
  "(6, 8)" : "white_concrete_powder",
  "(6, 9)" : "white_concrete_powder",
  "(6, 10)" : "white_wool",
  "(6, 11)" : "white_concrete_powder",
  "(6, 12)" : "white_concrete_powder",
  "(6, 13)" : "iron_block",
  "(6, 14)" : "white_glazed_terracotta",
  "(6, 15)" : "cyan_glazed_terracotta",
  "(6, 16)" : "stripped_warped_stem",
  "(6, 17)" : "sea_lantern",
  "(6, 18)" : "iron_block",
  "(6, 19)" : "iron_block",
  "(6, 20)" : "white_concrete_powder",
  "(6, 21)" : "white_wool",
  "(6, 22)" : "white_wool",
  "(6, 23)" : "white_wool",
  "(6, 24)" : "white_concrete_powder",
  "(6, 25)" : "white_concrete_powder",
  "(6, 26)" : "white_concrete_powder",
  "(6, 27)" : "white_concrete_powder",
  "(6, 28)" : "iron_block",
  "(6, 29)" : "iron_block",
  "(6, 30)" : "white_glazed_terracotta",
  "(6, 31)" : "cyan_glazed_terracotta",
  "(6, 32)" : "stripped_warped_stem",
  "(6, 33)" : "sea_lantern",
  "(6, 34)" : "iron_block",
  "(6, 35)" : "white_concrete_powder",
  "(6, 36)" : "white_concrete_powder",
  "(6, 37)" : "white_concrete_powder",
  "(6, 38)" : "white_wool",
  "(6, 39)" : "white_concrete_powder",
  "(6, 40)" : "white_concrete_powder",
  "(6, 41)" : "white_concrete_powder",
  "(6, 42)" : "white_wool",
  "(6, 43)" : "white_concrete_powder",
  "(6, 44)" : "white_concrete_powder",
  "(6, 45)" : "iron_block",
  "(6, 46)" : "white_glazed_terracotta",
  "(6, 47)" : "cyan_glazed_terracotta",
  "(6, 48)" : "stripped_warped_stem",
  "(6, 49)" : "sea_lantern",
  "(6, 50)" : "iron_block",
  "(6, 51)" : "white_concrete_powder",
  "(6, 52)" : "white_concrete_powder",
  "(6, 53)" : "white_concrete_powder",
  "(6, 54)" : "chiseled_quartz_block",
  "(6, 55)" : "white_concrete_powder",
  "(6, 56)" : "white_concrete_powder",
  "(6, 57)" : "chiseled_quartz_block",
  "(6, 58)" : "white_concrete_powder",
  "(6, 59)" : "white_concrete_powder",
  "(6, 60)" : "white_concrete_powder",
  "(6, 61)" : "iron_block",
  "(6, 62)" : "white_glazed_terracotta",
  "(6, 63)" : "cyan_glazed_terracotta",
  "(6, 64)" : "stripped_warped_stem",
  "(6, 65)" : "sea_lantern",
  "(6, 66)" : "iron_block",
  "(6, 67)" : "white_concrete_powder",
  "(6, 68)" : "white_concrete_powder",
  "(6, 69)" : "chiseled_quartz_block",
  "(6, 70)" : "white_concrete_powder",
  "(6, 71)" : "white_concrete_powder",
  "(6, 72)" : "white_wool",
  "(6, 73)" : "white_concrete_powder",
  "(6, 74)" : "iron_block",
  "(6, 75)" : "white_concrete_powder",
  "(6, 76)" : "white_concrete_powder",
  "(6, 77)" : "iron_block",
  "(6, 78)" : "white_glazed_terracotta",
  "(6, 79)" : "cyan_glazed_terracotta",
  "(7, 0)" : "stripped_warped_stem",
  "(7, 1)" : "white_concrete",
  "(7, 2)" : "iron_block",
  "(7, 3)" : "white_concrete_powder",
  "(7, 4)" : "white_concrete_powder",
  "(7, 5)" : "white_wool",
  "(7, 6)" : "white_concrete_powder",
  "(7, 7)" : "white_concrete_powder",
  "(7, 8)" : "white_concrete_powder",
  "(7, 9)" : "white_concrete_powder",
  "(7, 10)" : "white_wool",
  "(7, 11)" : "white_concrete_powder",
  "(7, 12)" : "white_concrete_powder",
  "(7, 13)" : "iron_block",
  "(7, 14)" : "white_concrete",
  "(7, 15)" : "cyan_glazed_terracotta",
  "(7, 16)" : "cyan_glazed_terracotta",
  "(7, 17)" : "white_concrete",
  "(7, 18)" : "iron_block",
  "(7, 19)" : "white_concrete_powder",
  "(7, 20)" : "white_concrete_powder",
  "(7, 21)" : "white_concrete_powder",
  "(7, 22)" : "white_wool",
  "(7, 23)" : "white_concrete_powder",
  "(7, 24)" : "white_concrete_powder",
  "(7, 25)" : "white_wool",
  "(7, 26)" : "white_wool",
  "(7, 27)" : "white_concrete_powder",
  "(7, 28)" : "white_concrete_powder",
  "(7, 29)" : "iron_block",
  "(7, 30)" : "white_concrete",
  "(7, 31)" : "cyan_glazed_terracotta",
  "(7, 32)" : "stripped_warped_stem",
  "(7, 33)" : "white_concrete",
  "(7, 34)" : "iron_block",
  "(7, 35)" : "white_concrete_powder",
  "(7, 36)" : "white_concrete_powder",
  "(7, 37)" : "white_concrete_powder",
  "(7, 38)" : "white_concrete_powder",
  "(7, 39)" : "white_concrete_powder",
  "(7, 40)" : "white_concrete_powder",
  "(7, 41)" : "iron_block",
  "(7, 42)" : "white_wool",
  "(7, 43)" : "white_concrete_powder",
  "(7, 44)" : "white_concrete_powder",
  "(7, 45)" : "iron_block",
  "(7, 46)" : "white_concrete",
  "(7, 47)" : "cyan_glazed_terracotta",
  "(7, 48)" : "stripped_warped_stem",
  "(7, 49)" : "white_concrete",
  "(7, 50)" : "iron_block",
  "(7, 51)" : "white_concrete_powder",
  "(7, 52)" : "white_concrete_powder",
  "(7, 53)" : "chiseled_quartz_block",
  "(7, 54)" : "white_concrete_powder",
  "(7, 55)" : "white_concrete_powder",
  "(7, 56)" : "white_wool",
  "(7, 57)" : "white_concrete_powder",
  "(7, 58)" : "chiseled_quartz_block",
  "(7, 59)" : "white_concrete_powder",
  "(7, 60)" : "white_concrete_powder",
  "(7, 61)" : "white_concrete_powder",
  "(7, 62)" : "white_concrete",
  "(7, 63)" : "cyan_glazed_terracotta",
  "(7, 64)" : "stripped_warped_stem",
  "(7, 65)" : "white_concrete",
  "(7, 66)" : "iron_block",
  "(7, 67)" : "white_concrete_powder",
  "(7, 68)" : "chiseled_quartz_block",
  "(7, 69)" : "white_concrete_powder",
  "(7, 70)" : "white_concrete_powder",
  "(7, 71)" : "white_concrete_powder",
  "(7, 72)" : "white_concrete_powder",
  "(7, 73)" : "white_concrete_powder",
  "(7, 74)" : "white_concrete_powder",
  "(7, 75)" : "chiseled_quartz_block",
  "(7, 76)" : "white_concrete_powder",
  "(7, 77)" : "iron_block",
  "(7, 78)" : "white_concrete",
  "(7, 79)" : "cyan_glazed_terracotta",
  "(8, 0)" : "emerald_ore",
  "(8, 1)" : "white_glazed_terracotta",
  "(8, 2)" : "white_concrete_powder",
  "(8, 3)" : "white_concrete_powder",
  "(8, 4)" : "white_concrete_powder",
  "(8, 5)" : "white_concrete_powder",
  "(8, 6)" : "white_concrete_powder",
  "(8, 7)" : "white_concrete_powder",
  "(8, 8)" : "white_concrete_powder",
  "(8, 9)" : "white_concrete_powder",
  "(8, 10)" : "white_concrete_powder",
  "(8, 11)" : "white_concrete_powder",
  "(8, 12)" : "white_concrete_powder",
  "(8, 13)" : "iron_block",
  "(8, 14)" : "white_concrete",
  "(8, 15)" : "cyan_glazed_terracotta",
  "(8, 16)" : "emerald_ore",
  "(8, 17)" : "white_glazed_terracotta",
  "(8, 18)" : "iron_block",
  "(8, 19)" : "white_concrete_powder",
  "(8, 20)" : "white_concrete_powder",
  "(8, 21)" : "white_concrete_powder",
  "(8, 22)" : "white_concrete_powder",
  "(8, 23)" : "white_concrete_powder",
  "(8, 24)" : "white_concrete_powder",
  "(8, 25)" : "white_concrete_powder",
  "(8, 26)" : "white_concrete_powder",
  "(8, 27)" : "white_concrete_powder",
  "(8, 28)" : "iron_block",
  "(8, 29)" : "iron_block",
  "(8, 30)" : "white_concrete",
  "(8, 31)" : "cyan_glazed_terracotta",
  "(8, 32)" : "emerald_ore",
  "(8, 33)" : "white_glazed_terracotta",
  "(8, 34)" : "iron_block",
  "(8, 35)" : "white_concrete_powder",
  "(8, 36)" : "white_concrete_powder",
  "(8, 37)" : "white_concrete_powder",
  "(8, 38)" : "white_concrete_powder",
  "(8, 39)" : "white_concrete_powder",
  "(8, 40)" : "white_concrete_powder",
  "(8, 41)" : "chiseled_quartz_block",
  "(8, 42)" : "white_concrete_powder",
  "(8, 43)" : "white_concrete_powder",
  "(8, 44)" : "white_concrete_powder",
  "(8, 45)" : "iron_block",
  "(8, 46)" : "white_concrete",
  "(8, 47)" : "cyan_glazed_terracotta",
  "(8, 48)" : "lapis_ore",
  "(8, 49)" : "white_glazed_terracotta",
  "(8, 50)" : "white_concrete_powder",
  "(8, 51)" : "white_concrete_powder",
  "(8, 52)" : "white_concrete_powder",
  "(8, 53)" : "chiseled_quartz_block",
  "(8, 54)" : "white_concrete_powder",
  "(8, 55)" : "white_wool",
  "(8, 56)" : "white_concrete_powder",
  "(8, 57)" : "white_concrete_powder",
  "(8, 58)" : "chiseled_quartz_block",
  "(8, 59)" : "white_concrete_powder",
  "(8, 60)" : "white_concrete_powder",
  "(8, 61)" : "iron_block",
  "(8, 62)" : "white_concrete",
  "(8, 63)" : "cyan_glazed_terracotta",
  "(8, 64)" : "emerald_ore",
  "(8, 65)" : "white_glazed_terracotta",
  "(8, 66)" : "iron_block",
  "(8, 67)" : "white_concrete_powder",
  "(8, 68)" : "chiseled_quartz_block",
  "(8, 69)" : "white_concrete_powder",
  "(8, 70)" : "white_wool",
  "(8, 71)" : "white_concrete_powder",
  "(8, 72)" : "white_concrete_powder",
  "(8, 73)" : "white_concrete_powder",
  "(8, 74)" : "white_concrete_powder",
  "(8, 75)" : "chiseled_quartz_block",
  "(8, 76)" : "white_concrete_powder",
  "(8, 77)" : "iron_block",
  "(8, 78)" : "white_concrete",
  "(8, 79)" : "cyan_glazed_terracotta",
  "(9, 0)" : "stripped_warped_stem",
  "(9, 1)" : "sea_lantern",
  "(9, 2)" : "iron_block",
  "(9, 3)" : "white_concrete_powder",
  "(9, 4)" : "white_concrete_powder",
  "(9, 5)" : "white_wool",
  "(9, 6)" : "white_wool",
  "(9, 7)" : "white_concrete_powder",
  "(9, 8)" : "white_wool",
  "(9, 9)" : "white_wool",
  "(9, 10)" : "white_wool",
  "(9, 11)" : "white_concrete_powder",
  "(9, 12)" : "white_concrete_powder",
  "(9, 13)" : "iron_block",
  "(9, 14)" : "white_glazed_terracotta",
  "(9, 15)" : "cyan_glazed_terracotta",
  "(9, 16)" : "stripped_warped_stem",
  "(9, 17)" : "sea_lantern",
  "(9, 18)" : "iron_block",
  "(9, 19)" : "white_concrete_powder",
  "(9, 20)" : "white_concrete_powder",
  "(9, 21)" : "white_concrete_powder",
  "(9, 22)" : "white_wool",
  "(9, 23)" : "white_wool",
  "(9, 24)" : "white_concrete_powder",
  "(9, 25)" : "white_wool",
  "(9, 26)" : "white_concrete_powder",
  "(9, 27)" : "white_concrete_powder",
  "(9, 28)" : "white_concrete_powder",
  "(9, 29)" : "iron_block",
  "(9, 30)" : "white_glazed_terracotta",
  "(9, 31)" : "cyan_glazed_terracotta",
  "(9, 32)" : "cyan_stained_glass",
  "(9, 33)" : "white_glazed_terracotta",
  "(9, 34)" : "iron_block",
  "(9, 35)" : "white_concrete_powder",
  "(9, 36)" : "white_concrete_powder",
  "(9, 37)" : "white_wool",
  "(9, 38)" : "white_wool",
  "(9, 39)" : "white_concrete_powder",
  "(9, 40)" : "chiseled_quartz_block",
  "(9, 41)" : "white_wool",
  "(9, 42)" : "white_concrete_powder",
  "(9, 43)" : "white_concrete_powder",
  "(9, 44)" : "white_concrete_powder",
  "(9, 45)" : "iron_block",
  "(9, 46)" : "white_glazed_terracotta",
  "(9, 47)" : "stripped_warped_stem",
  "(9, 48)" : "stripped_warped_stem",
  "(9, 49)" : "white_glazed_terracotta",
  "(9, 50)" : "iron_block",
  "(9, 51)" : "white_concrete_powder",
  "(9, 52)" : "white_concrete_powder",
  "(9, 53)" : "white_concrete_powder",
  "(9, 54)" : "chiseled_quartz_block",
  "(9, 55)" : "white_concrete_powder",
  "(9, 56)" : "white_concrete_powder",
  "(9, 57)" : "chiseled_quartz_block",
  "(9, 58)" : "white_concrete_powder",
  "(9, 59)" : "white_concrete_powder",
  "(9, 60)" : "white_concrete_powder",
  "(9, 61)" : "iron_block",
  "(9, 62)" : "white_glazed_terracotta",
  "(9, 63)" : "stripped_warped_stem",
  "(9, 64)" : "stripped_warped_stem",
  "(9, 65)" : "sea_lantern",
  "(9, 66)" : "iron_block",
  "(9, 67)" : "white_concrete_powder",
  "(9, 68)" : "white_concrete_powder",
  "(9, 69)" : "iron_block",
  "(9, 70)" : "white_concrete_powder",
  "(9, 71)" : "white_concrete_powder",
  "(9, 72)" : "white_concrete_powder",
  "(9, 73)" : "white_concrete_powder",
  "(9, 74)" : "iron_block",
  "(9, 75)" : "white_concrete_powder",
  "(9, 76)" : "white_concrete_powder",
  "(9, 77)" : "iron_block",
  "(9, 78)" : "white_glazed_terracotta",
  "(9, 79)" : "stripped_warped_stem",
  "(10, 0)" : "stripped_warped_stem",
  "(10, 1)" : "sea_lantern",
  "(10, 2)" : "iron_block",
  "(10, 3)" : "white_concrete_powder",
  "(10, 4)" : "white_concrete_powder",
  "(10, 5)" : "white_concrete_powder",
  "(10, 6)" : "white_wool",
  "(10, 7)" : "white_concrete_powder",
  "(10, 8)" : "white_concrete_powder",
  "(10, 9)" : "white_wool",
  "(10, 10)" : "white_concrete_powder",
  "(10, 11)" : "white_concrete_powder",
  "(10, 12)" : "white_concrete_powder",
  "(10, 13)" : "iron_block",
  "(10, 14)" : "sea_lantern",
  "(10, 15)" : "cyan_glazed_terracotta",
  "(10, 16)" : "stripped_warped_stem",
  "(10, 17)" : "sea_lantern",
  "(10, 18)" : "iron_block",
  "(10, 19)" : "white_concrete_powder",
  "(10, 20)" : "white_concrete_powder",
  "(10, 21)" : "white_concrete_powder",
  "(10, 22)" : "white_wool",
  "(10, 23)" : "white_concrete_powder",
  "(10, 24)" : "white_wool",
  "(10, 25)" : "white_concrete_powder",
  "(10, 26)" : "white_concrete_powder",
  "(10, 27)" : "white_concrete_powder",
  "(10, 28)" : "iron_block",
  "(10, 29)" : "iron_block",
  "(10, 30)" : "sea_lantern",
  "(10, 31)" : "cyan_glazed_terracotta",
  "(10, 32)" : "stripped_warped_stem",
  "(10, 33)" : "sea_lantern",
  "(10, 34)" : "iron_block",
  "(10, 35)" : "white_concrete_powder",
  "(10, 36)" : "white_concrete_powder",
  "(10, 37)" : "white_concrete_powder",
  "(10, 38)" : "white_concrete_powder",
  "(10, 39)" : "white_concrete_powder",
  "(10, 40)" : "white_concrete_powder",
  "(10, 41)" : "white_concrete_powder",
  "(10, 42)" : "white_concrete_powder",
  "(10, 43)" : "white_concrete_powder",
  "(10, 44)" : "white_concrete_powder",
  "(10, 45)" : "iron_block",
  "(10, 46)" : "white_glazed_terracotta",
  "(10, 47)" : "cyan_glazed_terracotta",
  "(10, 48)" : "stripped_warped_stem",
  "(10, 49)" : "white_glazed_terracotta",
  "(10, 50)" : "iron_block",
  "(10, 51)" : "white_concrete_powder",
  "(10, 52)" : "white_concrete_powder",
  "(10, 53)" : "white_concrete_powder",
  "(10, 54)" : "white_concrete_powder",
  "(10, 55)" : "chiseled_quartz_block",
  "(10, 56)" : "chiseled_quartz_block",
  "(10, 57)" : "white_concrete_powder",
  "(10, 58)" : "white_concrete_powder",
  "(10, 59)" : "white_concrete_powder",
  "(10, 60)" : "white_concrete_powder",
  "(10, 61)" : "iron_block",
  "(10, 62)" : "white_glazed_terracotta",
  "(10, 63)" : "cyan_glazed_terracotta",
  "(10, 64)" : "stripped_warped_stem",
  "(10, 65)" : "sea_lantern",
  "(10, 66)" : "iron_block",
  "(10, 67)" : "white_concrete_powder",
  "(10, 68)" : "white_concrete_powder",
  "(10, 69)" : "white_concrete_powder",
  "(10, 70)" : "chiseled_quartz_block",
  "(10, 71)" : "white_concrete_powder",
  "(10, 72)" : "white_concrete_powder",
  "(10, 73)" : "iron_block",
  "(10, 74)" : "white_concrete_powder",
  "(10, 75)" : "white_concrete_powder",
  "(10, 76)" : "white_concrete_powder",
  "(10, 77)" : "iron_block",
  "(10, 78)" : "white_glazed_terracotta",
  "(10, 79)" : "cyan_glazed_terracotta",
  "(11, 0)" : "emerald_ore",
  "(11, 1)" : "white_glazed_terracotta",
  "(11, 2)" : "white_concrete",
  "(11, 3)" : "white_concrete_powder",
  "(11, 4)" : "white_concrete_powder",
  "(11, 5)" : "white_concrete_powder",
  "(11, 6)" : "white_concrete_powder",
  "(11, 7)" : "white_concrete_powder",
  "(11, 8)" : "white_concrete_powder",
  "(11, 9)" : "white_concrete_powder",
  "(11, 10)" : "white_concrete_powder",
  "(11, 11)" : "white_concrete_powder",
  "(11, 12)" : "white_concrete_powder",
  "(11, 13)" : "iron_block",
  "(11, 14)" : "white_glazed_terracotta",
  "(11, 15)" : "lapis_ore",
  "(11, 16)" : "lapis_ore",
  "(11, 17)" : "white_glazed_terracotta",
  "(11, 18)" : "white_concrete",
  "(11, 19)" : "white_concrete_powder",
  "(11, 20)" : "iron_block",
  "(11, 21)" : "white_concrete_powder",
  "(11, 22)" : "white_concrete_powder",
  "(11, 23)" : "white_concrete_powder",
  "(11, 24)" : "white_concrete_powder",
  "(11, 25)" : "white_concrete_powder",
  "(11, 26)" : "white_concrete_powder",
  "(11, 27)" : "iron_block",
  "(11, 28)" : "white_concrete_powder",
  "(11, 29)" : "iron_block",
  "(11, 30)" : "white_glazed_terracotta",
  "(11, 31)" : "lapis_ore",
  "(11, 32)" : "emerald_ore",
  "(11, 33)" : "white_glazed_terracotta",
  "(11, 34)" : "white_concrete",
  "(11, 35)" : "iron_block",
  "(11, 36)" : "white_concrete_powder",
  "(11, 37)" : "white_concrete_powder",
  "(11, 38)" : "white_concrete_powder",
  "(11, 39)" : "white_concrete_powder",
  "(11, 40)" : "white_concrete_powder",
  "(11, 41)" : "white_concrete_powder",
  "(11, 42)" : "white_concrete_powder",
  "(11, 43)" : "white_concrete_powder",
  "(11, 44)" : "white_concrete_powder",
  "(11, 45)" : "iron_block",
  "(11, 46)" : "white_glazed_terracotta",
  "(11, 47)" : "lapis_ore",
  "(11, 48)" : "lapis_ore",
  "(11, 49)" : "white_glazed_terracotta",
  "(11, 50)" : "white_concrete",
  "(11, 51)" : "iron_block",
  "(11, 52)" : "white_concrete_powder",
  "(11, 53)" : "white_concrete_powder",
  "(11, 54)" : "white_concrete_powder",
  "(11, 55)" : "white_concrete_powder",
  "(11, 56)" : "white_concrete_powder",
  "(11, 57)" : "white_concrete_powder",
  "(11, 58)" : "white_concrete_powder",
  "(11, 59)" : "white_concrete_powder",
  "(11, 60)" : "white_concrete_powder",
  "(11, 61)" : "iron_block",
  "(11, 62)" : "white_glazed_terracotta",
  "(11, 63)" : "stripped_warped_stem",
  "(11, 64)" : "emerald_ore",
  "(11, 65)" : "white_glazed_terracotta",
  "(11, 66)" : "white_concrete",
  "(11, 67)" : "iron_block",
  "(11, 68)" : "white_concrete_powder",
  "(11, 69)" : "white_concrete_powder",
  "(11, 70)" : "white_concrete_powder",
  "(11, 71)" : "chiseled_quartz_block",
  "(11, 72)" : "white_concrete_powder",
  "(11, 73)" : "white_concrete_powder",
  "(11, 74)" : "white_concrete_powder",
  "(11, 75)" : "white_concrete_powder",
  "(11, 76)" : "white_concrete_powder",
  "(11, 77)" : "iron_block",
  "(11, 78)" : "white_glazed_terracotta",
  "(11, 79)" : "lapis_ore",
  "(12, 0)" : "stripped_warped_stem",
  "(12, 1)" : "sea_lantern",
  "(12, 2)" : "white_concrete",
  "(12, 3)" : "white_concrete",
  "(12, 4)" : "iron_block",
  "(12, 5)" : "white_concrete_powder",
  "(12, 6)" : "white_concrete_powder",
  "(12, 7)" : "white_concrete_powder",
  "(12, 8)" : "white_concrete_powder",
  "(12, 9)" : "white_concrete_powder",
  "(12, 10)" : "white_concrete_powder",
  "(12, 11)" : "white_concrete_powder",
  "(12, 12)" : "iron_block",
  "(12, 13)" : "white_glazed_terracotta",
  "(12, 14)" : "light_gray_glazed_terracotta",
  "(12, 15)" : "cyan_stained_glass",
  "(12, 16)" : "stripped_warped_stem",
  "(12, 17)" : "sea_lantern",
  "(12, 18)" : "white_concrete",
  "(12, 19)" : "white_concrete",
  "(12, 20)" : "iron_block",
  "(12, 21)" : "iron_block",
  "(12, 22)" : "white_concrete_powder",
  "(12, 23)" : "iron_block",
  "(12, 24)" : "white_concrete_powder",
  "(12, 25)" : "iron_block",
  "(12, 26)" : "iron_block",
  "(12, 27)" : "white_concrete_powder",
  "(12, 28)" : "iron_block",
  "(12, 29)" : "white_glazed_terracotta",
  "(12, 30)" : "light_gray_glazed_terracotta",
  "(12, 31)" : "cyan_stained_glass",
  "(12, 32)" : "stripped_warped_stem",
  "(12, 33)" : "sea_lantern",
  "(12, 34)" : "iron_block",
  "(12, 35)" : "white_concrete",
  "(12, 36)" : "iron_block",
  "(12, 37)" : "white_concrete_powder",
  "(12, 38)" : "white_concrete_powder",
  "(12, 39)" : "white_concrete_powder",
  "(12, 40)" : "white_concrete_powder",
  "(12, 41)" : "white_concrete_powder",
  "(12, 42)" : "white_concrete_powder",
  "(12, 43)" : "white_concrete_powder",
  "(12, 44)" : "iron_block",
  "(12, 45)" : "white_glazed_terracotta",
  "(12, 46)" : "light_gray_glazed_terracotta",
  "(12, 47)" : "cyan_stained_glass",
  "(12, 48)" : "lapis_ore",
  "(12, 49)" : "sea_lantern",
  "(12, 50)" : "iron_block",
  "(12, 51)" : "white_concrete",
  "(12, 52)" : "iron_block",
  "(12, 53)" : "white_concrete_powder",
  "(12, 54)" : "white_concrete_powder",
  "(12, 55)" : "white_concrete_powder",
  "(12, 56)" : "white_concrete_powder",
  "(12, 57)" : "white_concrete_powder",
  "(12, 58)" : "white_concrete_powder",
  "(12, 59)" : "white_concrete_powder",
  "(12, 60)" : "iron_block",
  "(12, 61)" : "white_glazed_terracotta",
  "(12, 62)" : "light_gray_glazed_terracotta",
  "(12, 63)" : "cyan_stained_glass",
  "(12, 64)" : "lapis_ore",
  "(12, 65)" : "sea_lantern",
  "(12, 66)" : "white_concrete",
  "(12, 67)" : "white_concrete",
  "(12, 68)" : "iron_block",
  "(12, 69)" : "white_concrete_powder",
  "(12, 70)" : "white_concrete_powder",
  "(12, 71)" : "white_concrete_powder",
  "(12, 72)" : "white_concrete_powder",
  "(12, 73)" : "white_concrete_powder",
  "(12, 74)" : "white_concrete_powder",
  "(12, 75)" : "white_concrete_powder",
  "(12, 76)" : "iron_block",
  "(12, 77)" : "white_glazed_terracotta",
  "(12, 78)" : "light_gray_glazed_terracotta",
  "(12, 79)" : "lapis_ore",
  "(13, 0)" : "stripped_warped_stem",
  "(13, 1)" : "prismarine_bricks",
  "(13, 2)" : "light_gray_glazed_terracotta",
  "(13, 3)" : "white_concrete",
  "(13, 4)" : "iron_block",
  "(13, 5)" : "iron_block",
  "(13, 6)" : "iron_block",
  "(13, 7)" : "iron_block",
  "(13, 8)" : "iron_block",
  "(13, 9)" : "white_concrete_powder",
  "(13, 10)" : "iron_block",
  "(13, 11)" : "iron_block",
  "(13, 12)" : "white_concrete",
  "(13, 13)" : "light_gray_glazed_terracotta",
  "(13, 14)" : "prismarine_bricks",
  "(13, 15)" : "cyan_glazed_terracotta",
  "(13, 16)" : "stripped_warped_stem",
  "(13, 17)" : "prismarine_bricks",
  "(13, 18)" : "sea_lantern",
  "(13, 19)" : "white_concrete",
  "(13, 20)" : "white_concrete",
  "(13, 21)" : "iron_block",
  "(13, 22)" : "iron_block",
  "(13, 23)" : "iron_block",
  "(13, 24)" : "iron_block",
  "(13, 25)" : "iron_block",
  "(13, 26)" : "iron_block",
  "(13, 27)" : "iron_block",
  "(13, 28)" : "white_concrete",
  "(13, 29)" : "light_gray_glazed_terracotta",
  "(13, 30)" : "prismarine_bricks",
  "(13, 31)" : "cyan_glazed_terracotta",
  "(13, 32)" : "stripped_warped_stem",
  "(13, 33)" : "prismarine_bricks",
  "(13, 34)" : "sea_lantern",
  "(13, 35)" : "white_concrete",
  "(13, 36)" : "white_concrete",
  "(13, 37)" : "iron_block",
  "(13, 38)" : "iron_block",
  "(13, 39)" : "iron_block",
  "(13, 40)" : "iron_block",
  "(13, 41)" : "iron_block",
  "(13, 42)" : "iron_block",
  "(13, 43)" : "iron_block",
  "(13, 44)" : "white_glazed_terracotta",
  "(13, 45)" : "light_gray_glazed_terracotta",
  "(13, 46)" : "prismarine_bricks",
  "(13, 47)" : "cyan_glazed_terracotta",
  "(13, 48)" : "stripped_warped_stem",
  "(13, 49)" : "prismarine_bricks",
  "(13, 50)" : "light_gray_glazed_terracotta",
  "(13, 51)" : "white_concrete",
  "(13, 52)" : "white_concrete",
  "(13, 53)" : "iron_block",
  "(13, 54)" : "iron_block",
  "(13, 55)" : "iron_block",
  "(13, 56)" : "iron_block",
  "(13, 57)" : "iron_block",
  "(13, 58)" : "iron_block",
  "(13, 59)" : "iron_block",
  "(13, 60)" : "white_concrete",
  "(13, 61)" : "light_gray_glazed_terracotta",
  "(13, 62)" : "prismarine_bricks",
  "(13, 63)" : "cyan_glazed_terracotta",
  "(13, 64)" : "stripped_warped_stem",
  "(13, 65)" : "prismarine_bricks",
  "(13, 66)" : "light_gray_glazed_terracotta",
  "(13, 67)" : "white_concrete",
  "(13, 68)" : "white_concrete",
  "(13, 69)" : "iron_block",
  "(13, 70)" : "iron_block",
  "(13, 71)" : "iron_block",
  "(13, 72)" : "iron_block",
  "(13, 73)" : "iron_block",
  "(13, 74)" : "iron_block",
  "(13, 75)" : "iron_block",
  "(13, 76)" : "white_concrete",
  "(13, 77)" : "light_gray_glazed_terracotta",
  "(13, 78)" : "prismarine_bricks",
  "(13, 79)" : "cyan_glazed_terracotta",
  "(14, 0)" : "emerald_ore",
  "(14, 1)" : "stripped_warped_stem",
  "(14, 2)" : "prismarine_bricks",
  "(14, 3)" : "light_gray_glazed_terracotta",
  "(14, 4)" : "white_glazed_terracotta",
  "(14, 5)" : "sea_lantern",
  "(14, 6)" : "sea_lantern",
  "(14, 7)" : "white_concrete",
  "(14, 8)" : "white_glazed_terracotta",
  "(14, 9)" : "sea_lantern",
  "(14, 10)" : "white_glazed_terracotta",
  "(14, 11)" : "sea_lantern",
  "(14, 12)" : "light_gray_glazed_terracotta",
  "(14, 13)" : "prismarine_bricks",
  "(14, 14)" : "stripped_warped_stem",
  "(14, 15)" : "cyan_stained_glass",
  "(14, 16)" : "emerald_ore",
  "(14, 17)" : "stripped_warped_stem",
  "(14, 18)" : "prismarine_bricks",
  "(14, 19)" : "light_gray_glazed_terracotta",
  "(14, 20)" : "white_glazed_terracotta",
  "(14, 21)" : "sea_lantern",
  "(14, 22)" : "sea_lantern",
  "(14, 23)" : "white_concrete",
  "(14, 24)" : "white_glazed_terracotta",
  "(14, 25)" : "sea_lantern",
  "(14, 26)" : "white_glazed_terracotta",
  "(14, 27)" : "sea_lantern",
  "(14, 28)" : "light_gray_glazed_terracotta",
  "(14, 29)" : "prismarine_bricks",
  "(14, 30)" : "stripped_warped_stem",
  "(14, 31)" : "cyan_stained_glass",
  "(14, 32)" : "emerald_ore",
  "(14, 33)" : "stripped_warped_stem",
  "(14, 34)" : "prismarine_bricks",
  "(14, 35)" : "light_gray_glazed_terracotta",
  "(14, 36)" : "white_glazed_terracotta",
  "(14, 37)" : "sea_lantern",
  "(14, 38)" : "sea_lantern",
  "(14, 39)" : "white_concrete",
  "(14, 40)" : "white_glazed_terracotta",
  "(14, 41)" : "sea_lantern",
  "(14, 42)" : "white_glazed_terracotta",
  "(14, 43)" : "sea_lantern",
  "(14, 44)" : "light_gray_glazed_terracotta",
  "(14, 45)" : "prismarine_bricks",
  "(14, 46)" : "stripped_warped_stem",
  "(14, 47)" : "lapis_ore",
  "(14, 48)" : "emerald_ore",
  "(14, 49)" : "lapis_ore",
  "(14, 50)" : "prismarine_bricks",
  "(14, 51)" : "light_gray_glazed_terracotta",
  "(14, 52)" : "white_glazed_terracotta",
  "(14, 53)" : "sea_lantern",
  "(14, 54)" : "white_glazed_terracotta",
  "(14, 55)" : "white_concrete",
  "(14, 56)" : "white_glazed_terracotta",
  "(14, 57)" : "sea_lantern",
  "(14, 58)" : "white_glazed_terracotta",
  "(14, 59)" : "sea_lantern",
  "(14, 60)" : "light_gray_glazed_terracotta",
  "(14, 61)" : "prismarine_bricks",
  "(14, 62)" : "stripped_warped_stem",
  "(14, 63)" : "cyan_stained_glass",
  "(14, 64)" : "emerald_ore",
  "(14, 65)" : "stripped_warped_stem",
  "(14, 66)" : "prismarine_bricks",
  "(14, 67)" : "light_gray_glazed_terracotta",
  "(14, 68)" : "white_glazed_terracotta",
  "(14, 69)" : "sea_lantern",
  "(14, 70)" : "sea_lantern",
  "(14, 71)" : "white_concrete",
  "(14, 72)" : "white_glazed_terracotta",
  "(14, 73)" : "sea_lantern",
  "(14, 74)" : "white_glazed_terracotta",
  "(14, 75)" : "sea_lantern",
  "(14, 76)" : "light_gray_glazed_terracotta",
  "(14, 77)" : "prismarine_bricks",
  "(14, 78)" : "stripped_warped_stem",
  "(14, 79)" : "lapis_ore",
  "(15, 0)" : "emerald_ore",
  "(15, 1)" : "stripped_warped_stem",
  "(15, 2)" : "stripped_warped_stem",
  "(15, 3)" : "cyan_glazed_terracotta",
  "(15, 4)" : "cyan_glazed_terracotta",
  "(15, 5)" : "cyan_glazed_terracotta",
  "(15, 6)" : "cyan_glazed_terracotta",
  "(15, 7)" : "cyan_stained_glass",
  "(15, 8)" : "stripped_warped_stem",
  "(15, 9)" : "stripped_warped_stem",
  "(15, 10)" : "cyan_glazed_terracotta",
  "(15, 11)" : "cyan_glazed_terracotta",
  "(15, 12)" : "cyan_glazed_terracotta",
  "(15, 13)" : "cyan_glazed_terracotta",
  "(15, 14)" : "lapis_ore",
  "(15, 15)" : "stripped_warped_stem",
  "(15, 16)" : "emerald_ore",
  "(15, 17)" : "stripped_warped_stem",
  "(15, 18)" : "stripped_warped_stem",
  "(15, 19)" : "cyan_glazed_terracotta",
  "(15, 20)" : "cyan_glazed_terracotta",
  "(15, 21)" : "stripped_warped_stem",
  "(15, 22)" : "cyan_glazed_terracotta",
  "(15, 23)" : "cyan_stained_glass",
  "(15, 24)" : "stripped_warped_stem",
  "(15, 25)" : "stripped_warped_stem",
  "(15, 26)" : "cyan_glazed_terracotta",
  "(15, 27)" : "cyan_glazed_terracotta",
  "(15, 28)" : "cyan_glazed_terracotta",
  "(15, 29)" : "cyan_glazed_terracotta",
  "(15, 30)" : "cyan_stained_glass",
  "(15, 31)" : "stripped_warped_stem",
  "(15, 32)" : "emerald_ore",
  "(15, 33)" : "cyan_glazed_terracotta",
  "(15, 34)" : "stripped_warped_stem",
  "(15, 35)" : "cyan_glazed_terracotta",
  "(15, 36)" : "cyan_glazed_terracotta",
  "(15, 37)" : "cyan_glazed_terracotta",
  "(15, 38)" : "cyan_glazed_terracotta",
  "(15, 39)" : "cyan_stained_glass",
  "(15, 40)" : "cyan_stained_glass",
  "(15, 41)" : "stripped_warped_stem",
  "(15, 42)" : "cyan_glazed_terracotta",
  "(15, 43)" : "cyan_glazed_terracotta",
  "(15, 44)" : "cyan_glazed_terracotta",
  "(15, 45)" : "cyan_glazed_terracotta",
  "(15, 46)" : "lapis_ore",
  "(15, 47)" : "stripped_warped_stem",
  "(15, 48)" : "emerald_ore",
  "(15, 49)" : "stripped_warped_stem",
  "(15, 50)" : "stripped_warped_stem",
  "(15, 51)" : "cyan_glazed_terracotta",
  "(15, 52)" : "cyan_glazed_terracotta",
  "(15, 53)" : "cyan_glazed_terracotta",
  "(15, 54)" : "cyan_glazed_terracotta",
  "(15, 55)" : "cyan_stained_glass",
  "(15, 56)" : "stripped_warped_stem",
  "(15, 57)" : "cyan_stained_glass",
  "(15, 58)" : "cyan_glazed_terracotta",
  "(15, 59)" : "cyan_glazed_terracotta",
  "(15, 60)" : "cyan_glazed_terracotta",
  "(15, 61)" : "cyan_glazed_terracotta",
  "(15, 62)" : "lapis_ore",
  "(15, 63)" : "cyan_glazed_terracotta",
  "(15, 64)" : "emerald_ore",
  "(15, 65)" : "stripped_warped_stem",
  "(15, 66)" : "stripped_warped_stem",
  "(15, 67)" : "cyan_glazed_terracotta",
  "(15, 68)" : "cyan_glazed_terracotta",
  "(15, 69)" : "stripped_warped_stem",
  "(15, 70)" : "cyan_glazed_terracotta",
  "(15, 71)" : "cyan_stained_glass",
  "(15, 72)" : "stripped_warped_stem",
  "(15, 73)" : "stripped_warped_stem",
  "(15, 74)" : "cyan_glazed_terracotta",
  "(15, 75)" : "cyan_glazed_terracotta",
  "(15, 76)" : "cyan_glazed_terracotta",
  "(15, 77)" : "cyan_glazed_terracotta",
  "(15, 78)" : "lapis_ore",
  "(15, 79)" : "stripped_warped_stem"
}